kestrel/__init__.py
kestrel/cli.py
kestrel/config.py
kestrel/config.yaml
kestrel/deprecating.py
kestrel/exceptions.py
kestrel/session.py
kestrel/utils.py
kestrel/absinterface/__init__.py
kestrel/absinterface/manager.py
kestrel/analytics/__init__.py
kestrel/analytics/interface.py
kestrel/analytics/manager.py
kestrel/codegen/__init__.py
kestrel/codegen/commands.py
kestrel/codegen/data.py
kestrel/codegen/display.py
kestrel/codegen/prefetch.py
kestrel/codegen/queries.py
kestrel/codegen/relations.py
kestrel/codegen/summary.py
kestrel/datasource/__init__.py
kestrel/datasource/interface.py
kestrel/datasource/manager.py
kestrel/datasource/retstruct.py
kestrel/semantics/__init__.py
kestrel/semantics/completor.py
kestrel/semantics/processor.py
kestrel/semantics/reference.py
kestrel/symboltable/__init__.py
kestrel/symboltable/symtable.py
kestrel/symboltable/variable.py
kestrel/syntax/__init__.py
kestrel/syntax/ecgpattern.lark
kestrel/syntax/ecgpattern.py
kestrel/syntax/kestrel.lark
kestrel/syntax/parser.py
kestrel/syntax/reference.py
kestrel/syntax/utils.py
kestrel_core-1.8.2.dist-info/METADATA
kestrel_core-1.8.2.dist-info/WHEEL
kestrel_core-1.8.2.dist-info/entry_points.txt
kestrel_core-1.8.2.dist-info/top_level.txt
kestrel_core-1.8.2.dist-info/RECORD
