Metadata-Version: 2.1
Name: kestrel_core
Version: 1.8.2
Summary: Kestrel Threat Hunting Language
Maintainer-email: Xiaokui Shu <xiaokui.shu@ibm.com>, Paul Coccoli <pcoccoli@us.ibm.com>
License: Apache 2.0 License
Project-URL: Homepage, https://github.com/opencybersecurityalliance/kestrel-lang
Project-URL: Documentation, https://kestrel.readthedocs.io/
Project-URL: Repository, https://github.com/opencybersecurityalliance/kestrel-lang.git
Keywords: kestrel,language,DSL,cybersecurity,threat hunting,huntflow,entity
Classifier: Topic :: Security
Classifier: Operating System :: OS Independent
Classifier: Development Status :: 4 - Beta
Classifier: Programming Language :: Python :: 3
Requires-Python: >=3.8
Requires-Dist: typeguard>=4.2.1
Requires-Dist: pyyaml>=6.0.1
Requires-Dist: lark>=1.1.9
Requires-Dist: pandas>=2.0.3
Requires-Dist: pyarrow>=15.0.2
Requires-Dist: tabulate>=0.9.0
Requires-Dist: firepit>=2.3.33
Provides-Extra: test
Requires-Dist: pytest; extra == "test"
Requires-Dist: kestrel_datasource_stixbundle; extra == "test"
Requires-Dist: kestrel_analytics_python; extra == "test"
